Ver_1/RTL_crypto_hashblocks_sha256.v
`timescale 1ns / 1ps

module RTL_crypto_hashblocks_sha256(
												input wire 			CLK,
                                    input	wire			RST,
                                    input	wire			start_in,
                                    input	wire	[511:0]	message_in,
                                    input	wire	[255:0]	digest_in,
                                    output	reg		[255:0]	digest_out,
                                    output	reg            	valid_out
);

    reg  [6:0] 		round_reg;
    reg				round_add;
        
    reg [511:0] 	message_reg;	
        
    wire [31:0] 	W0_wr, W1_wr, W2_wr, W3_wr, W4_wr, W5_wr, W6_wr, W7_wr, W8_wr, W9_wr, W10_wr, W11_wr, W12_wr, W13_wr, W14_wr, W15_wr, W16_wr;

    
    wire [31:0] 	a_wr, b_wr, c_wr, d_wr, e_wr, f_wr, g_wr, h_wr, a_new_wr, e_new_wr;

    reg [255:0] 	digest_reg;	
    reg [255:0] 	digest_init_reg;
    
 
   
    wire [31:0] 	sigma0_wr;
	wire [31:0] 	sigma1_wr;
	
	wire [31:0] 	SIGMA0_wr;
	wire [31:0] 	SIGMA1_wr;
	
	wire [31:0]  	Ch_wr;
	wire [31:0]  	Maj_wr;
	
    reg	 [31:0]		K_reg;

    // Controller
    always @ (posedge CLK)
    begin 
        if(RST == 1'b0) begin
            round_reg 			<= 7'b0;
            round_add			<= 1'b0;
        end
        else begin
            if(start_in) begin
                round_add			<= 1'b1;
                round_reg 			<= round_reg + 1'b1;
            end
            else if (round_reg == 7'd65) begin
                round_reg  		<= 7'b0;
                round_add		<= 1'b0;
            end
            else begin
                round_add			<= round_add;
                round_reg 			<= round_reg + round_add;
            end
        end
	end

    // Expander

	assign W0_wr  = (start_in) ? message_in[511:480] : message_reg[511:480];
	assign W1_wr  = (start_in) ? message_in[479:448] : message_reg[479:448];
	assign W2_wr  = (start_in) ? message_in[447:416] : message_reg[447:416];
	assign W3_wr  = (start_in) ? message_in[415:384] : message_reg[415:384];
	assign W4_wr  = (start_in) ? message_in[383:352] : message_reg[383:352];
	assign W5_wr  = (start_in) ? message_in[351:320] : message_reg[351:320];
	assign W6_wr  = (start_in) ? message_in[319:288] : message_reg[319:288];
	assign W7_wr  = (start_in) ? message_in[287:256] : message_reg[287:256];
	assign W8_wr  = (start_in) ? message_in[255:224] : message_reg[255:224];
	assign W9_wr  = (start_in) ? message_in[223:192] : message_reg[223:192];
	assign W10_wr = (start_in) ? message_in[191:160] : message_reg[191:160];
	assign W11_wr = (start_in) ? message_in[159:128] : message_reg[159:128];
	assign W12_wr = (start_in) ? message_in[127:96 ] : message_reg[127:96 ];
	assign W13_wr = (start_in) ? message_in[95:64  ] : message_reg[95:64  ];
	assign W14_wr = (start_in) ? message_in[63:32  ] : message_reg[63:32  ];
	assign W15_wr = (start_in) ? message_in[31:0   ] : message_reg[31:0   ];


//    RTL_EXPAND_32 RTL_EXPAND_32_0(.W0(), .W1(), .W2(), .W3(), .W4(), .W5(), .W6(), .W7(), .W8(), .W9(), .W10(), .W11(), .W12(), .W13(), .W14(), .W15(),
//   
/*                               .W0_out(), .W1_out(), .W2_out(), .W3_out(), .W4_out(), .W5_out(), .W6_out(), .W7_out(), .W8_out(), .W9_out(), .W10_out(), .W11_out(), .W12_out(), .W13_out(), .W14_out(), .W15_out());
    RTL_Msigma0_32 Msigma0_32_0(.x(W1_wr),.result(sigma0_out));
    RTL_Msigma1_32 Msigma1_32_0(.x(W14_wr),.result(sigma1_out));


    
    assign W16_wr = sigma0_out + W0_wr + sigma1_out + W9_wr;   
    */
    assign sigma0_wr = {W1_wr[6:0],W1_wr[31:7],W1_wr[6:0],W1_wr[31:7]}^{W1_wr[17:0],W1_wr[31:18],W1_wr[17:0],W1_wr[31:18]}^{3'b000,W1_wr[31:3],3'b000,W1_wr[31:3]};
	assign sigma1_wr = {W14_wr[16:0],W14_wr[31:17],W14_wr[16:0],W14_wr[31:17]}^{W14_wr[18:0],W14_wr[31:19],W14_wr[18:0],W14_wr[31:19]}^{10'b0000000000,W14_wr[31:10],10'b0000000000,W14_wr[31:10]};

	assign W16_wr = sigma0_wr + sigma1_wr + W0_wr + W9_wr; 
	
   always @(posedge CLK or negedge RST) 
	begin
		if(RST == 1'b0) begin
			message_reg 	<= 512'b0;
		end
		else begin
			message_reg <= {W1_wr, W2_wr, W3_wr, W4_wr, W5_wr, W6_wr, W7_wr, W8_wr, W9_wr, W10_wr, W11_wr, W12_wr, W13_wr, W14_wr, W15_wr, W16_wr};
		end
	end
    
    // F_32
    assign a_wr = (start_in) ? digest_in[255:224] : digest_reg[255:224];
	assign b_wr = (start_in) ? digest_in[223:192] : digest_reg[223:192];
	assign c_wr = (start_in) ? digest_in[191:160] : digest_reg[191:160];
	assign d_wr = (start_in) ? digest_in[159:128] : digest_reg[159:128];
	assign e_wr = (start_in) ? digest_in[127:96 ] : digest_reg[127:96 ];
	assign f_wr = (start_in) ? digest_in[95:64  ] : digest_reg[95:64  ];
	assign g_wr = (start_in) ? digest_in[63:32  ] : digest_reg[63:32  ];
	assign h_wr = (start_in) ? digest_in[31:0   ] : digest_reg[31:0   ];
	
	/*
    RTL_Sigma0_32 Sigma0_F32(.x(a_wr),.result(F_SIGMA0_out));
    RTL_Sigma1_32 Sigma1_F32(.x(e_wr),.result(F_SIGMA1_out));
    RTL_Ch Ch_F32(.x(e_wr),.y(f_wr),.z(g_wr),.result(Ch_out));
    RTL_Maj Maj_F32(.x(a_wr),.y(b_wr),.z(c_wr),.result(Maj_out));
    
    assign T1_wr = h_wr + F_SIGMA1_out + Ch_out + K_reg + W0_wr;
    assign T2_wr = F_SIGMA0_out + Maj_out;
    assign a_new_wr = T1_wr + T2_wr;
    assign e_new_wr = d_wr + T1_wr;
    */
    assign SIGMA1_wr 	= {e_wr[5:0],e_wr[31:6]} ^ {e_wr[10:0], e_wr[31:11]} ^ {e_wr[24:0], e_wr[31:25]};
	assign SIGMA0_wr 	= {a_wr[1:0], a_wr[31:2]} ^ {a_wr[12:0], a_wr[31:13]} ^ {a_wr[21:0], a_wr[31:22]};
	assign Ch_wr   	 	= (e_wr & f_wr) ^ ((~e_wr) & g_wr);
	assign Maj_wr	 	= (a_wr & b_wr) ^ (a_wr & c_wr) ^ (b_wr & c_wr);

	assign a_new_wr 		= SIGMA0_wr + Maj_wr + K_reg + W0_wr + h_wr + SIGMA1_wr + Ch_wr;
	assign e_new_wr 		= K_reg + W0_wr + h_wr + SIGMA1_wr + Ch_wr + d_wr;

    always @(posedge CLK or negedge RST)	
	begin
		if(RST == 1'b0) begin
			digest_reg			<= 256'h0;
			digest_init_reg	    <= 256'h0;
			digest_out			<= 256'h0;
			valid_out			<= 1'b0;
		end
		else begin
			digest_reg		<= {a_new_wr,a_wr,b_wr,c_wr,e_new_wr,e_wr,f_wr,g_wr};
			
			if(start_in) begin								
				digest_init_reg	    <= digest_in;
				digest_out			<= 256'h0;
				valid_out			<= 1'b0;
			end
			else if(round_reg == 7'd64) begin
			
				digest_out[255:224] <= digest_init_reg[255:224] + digest_reg[255:224];
				digest_out[223:192] <= digest_init_reg[223:192] + digest_reg[223:192];
				digest_out[191:160] <= digest_init_reg[191:160] + digest_reg[191:160];
				digest_out[159:128] <= digest_init_reg[159:128] + digest_reg[159:128];
				digest_out[127:96] 	<= digest_init_reg[127:96]  + digest_reg[127:96];
				digest_out[95:64] 	<= digest_init_reg[95:64]   + digest_reg[95:64];  
				digest_out[63:32]	<= digest_init_reg[63:32]   + digest_reg[63:32];  
				digest_out[31:0] 	<= digest_init_reg[31:0]    + digest_reg[31:0];   
				
				valid_out			<= 1'b1;
			end
			else begin				
				digest_init_reg	    <= digest_init_reg;				
				//digest_out			<= 256'h0;
				digest_out			<= digest_out;
				valid_out			<= 1'b0;
			end
		end
	end
    
       
    always @*
    begin
        case(round_reg)
            7'd00: K_reg <= 32'h428a2f98;
            7'd01: K_reg <= 32'h71374491;
            7'd02: K_reg <= 32'hb5c0fbcf;
            7'd03: K_reg <= 32'he9b5dba5;
            7'd04: K_reg <= 32'h3956c25b;
            7'd05: K_reg <= 32'h59f111f1;
            7'd06: K_reg <= 32'h923f82a4;
            7'd07: K_reg <= 32'hab1c5ed5;
            7'd08: K_reg <= 32'hd807aa98;
            7'd09: K_reg <= 32'h12835b01;
            7'd10: K_reg <= 32'h243185be;
            7'd11: K_reg <= 32'h550c7dc3;
            7'd12: K_reg <= 32'h72be5d74;
            7'd13: K_reg <= 32'h80deb1fe;
            7'd14: K_reg <= 32'h9bdc06a7;
            7'd15: K_reg <= 32'hc19bf174;
            7'd16: K_reg <= 32'he49b69c1;
            7'd17: K_reg <= 32'hefbe4786;
            7'd18: K_reg <= 32'h0fc19dc6;
            7'd19: K_reg <= 32'h240ca1cc;
            7'd20: K_reg <= 32'h2de92c6f;
            7'd21: K_reg <= 32'h4a7484aa;
            7'd22: K_reg <= 32'h5cb0a9dc;
            7'd23: K_reg <= 32'h76f988da;
            7'd24: K_reg <= 32'h983e5152;
            7'd25: K_reg <= 32'ha831c66d;
            7'd26: K_reg <= 32'hb00327c8;
            7'd27: K_reg <= 32'hbf597fc7;
            7'd28: K_reg <= 32'hc6e00bf3;
            7'd29: K_reg <= 32'hd5a79147;
            7'd30: K_reg <= 32'h06ca6351;
            7'd31: K_reg <= 32'h14292967;
            7'd32: K_reg <= 32'h27b70a85;
            7'd33: K_reg <= 32'h2e1b2138;
            7'd34: K_reg <= 32'h4d2c6dfc;
            7'd35: K_reg <= 32'h53380d13;
            7'd36: K_reg <= 32'h650a7354;
            7'd37: K_reg <= 32'h766a0abb;
            7'd38: K_reg <= 32'h81c2c92e;
            7'd39: K_reg <= 32'h92722c85;
            7'd40: K_reg <= 32'ha2bfe8a1;
            7'd41: K_reg <= 32'ha81a664b;
            7'd42: K_reg <= 32'hc24b8b70;
            7'd43: K_reg <= 32'hc76c51a3;
            7'd44: K_reg <= 32'hd192e819;
            7'd45: K_reg <= 32'hd6990624;
            7'd46: K_reg <= 32'hf40e3585;
            7'd47: K_reg <= 32'h106aa070;
            7'd48: K_reg <= 32'h19a4c116;
            7'd49: K_reg <= 32'h1e376c08;
            7'd50: K_reg <= 32'h2748774c;
            7'd51: K_reg <= 32'h34b0bcb5;
            7'd52: K_reg <= 32'h391c0cb3;
            7'd53: K_reg <= 32'h4ed8aa4a;
            7'd54: K_reg <= 32'h5b9cca4f;
            7'd55: K_reg <= 32'h682e6ff3;
            7'd56: K_reg <= 32'h748f82ee;
            7'd57: K_reg <= 32'h78a5636f;
            7'd58: K_reg <= 32'h84c87814;
            7'd59: K_reg <= 32'h8cc70208;
            7'd60: K_reg <= 32'h90befffa;
            7'd61: K_reg <= 32'ha4506ceb;
            7'd62: K_reg <= 32'hbef9a3f7;
            7'd63: K_reg <= 32'hc67178f2;
            default: K_reg <= 32'b0;
        endcase
    end

endmodule

Ver_1/tb_RTL_crypto_hashblocks_sha256.v
`timescale 1ns/1ps

module tb_RTL_crypto_hashblocks_sha256;

  // DUT ports
  reg         CLK;
  reg         RST;       // active-low
  reg         start_in;
  reg  [511:0] message_in;
  reg  [255:0] digest_in;
  wire [255:0] digest_out;
  wire        valid_out;

  // Clock generation: 100 MHz
  initial CLK = 1'b0;
  always #5 CLK = ~CLK; // 10ns period

  // Device Under Test
  RTL_crypto_hashblocks_sha256 dut (
    .CLK(CLK),
    .RST(RST),
    .start_in(start_in),
    .message_in(message_in),
    .digest_in(digest_in),
    .digest_out(digest_out),
    .valid_out(valid_out)
  );

  // SHA-256 initial IV (H0..H7)
  localparam [255:0] SHA256_IV = {
    32'h6a09e667, 32'hbb67ae85, 32'h3c6ef372, 32'ha54ff53a,
    32'h510e527f, 32'h9b05688c, 32'h1f83d9ab, 32'h5be0cd19
  };

  // Test vector: "abc" (single block) padded
  // W[0]..W[15] big-endian, packed MSW->LSW to match DUT slices
  localparam [511:0] BLOCK_ABC = {
    32'h61626380, 32'h00000000, 32'h00000000, 32'h00000000,
    32'h00000000, 32'h00000000, 32'h00000000, 32'h00000000,
    32'h00000000, 32'h00000000, 32'h00000000, 32'h00000000,
    32'h00000000, 32'h00000000, 32'h00000000, 32'h00000018
  };

  // Expected SHA-256("abc") digest
  localparam [255:0] DIGEST_ABC = 256'hba7816bf8f01cfea414140de5dae2223b00361a396177a9cb410ff61f20015ad;

  // Simple reset, drive, and check
  initial begin
    // VCD dump for GTKWave
    $dumpfile("tb_sha256.vcd");
    $dumpvars(0, tb_RTL_crypto_hashblocks_sha256);

    // Init
    RST       = 1'b0; // active-low reset asserted
    start_in  = 1'b0;
    message_in = {512{1'b0}};
    digest_in  = {256{1'b0}};

    // Hold reset
    repeat (4) @(posedge CLK);
    RST = 1'b1; // deassert reset

    // Apply inputs for test "abc"
    @(posedge CLK);
    digest_in  <= SHA256_IV;
    message_in <= BLOCK_ABC;

    // Pulse start for 1 cycle
    @(posedge CLK);
    start_in <= 1'b1;
    @(posedge CLK);
    start_in <= 1'b0;

    // Wait for valid flag
    wait (valid_out === 1'b1);
    @(posedge CLK); // sample on clock

    // Report result
    $display("Time %0t: digest_out = %064h", $time, digest_out);

    if (digest_out === DIGEST_ABC) begin
      $display("[PASS] SHA-256(\"abc\") matches expected.");
    end else begin
      $display("[FAIL] Expected %064h", DIGEST_ABC);
    end

    // Small delay then finish
    repeat (5) @(posedge CLK);
    $finish;
  end

endmodule

Ver_2/tb_sha256.vcd
$date
	Sun Sep 21 14:00:28 2025
$end
$version
	Icarus Verilog
$end
$timescale
	1ps
$end
$scope module tb_RTL_crypto_hashblocks_sha256 $end
$var wire 1 ! valid_out $end
$var wire 256 " digest_out [255:0] $end
$var reg 1 # CLK $end
$var reg 1 $ RST $end
$var reg 256 % digest_in [255:0] $end
$var reg 512 & message_in [511:0] $end
$var reg 1 ' start_in $end
$scope module dut $end
$var wire 1 # CLK $end
$var wire 32 ( Ch_wr [31:0] $end
$var wire 32 ) Maj_wr [31:0] $end
$var wire 1 $ RST $end
$var wire 32 * SIGMA0_wr [31:0] $end
$var wire 32 + SIGMA1_wr [31:0] $end
$var wire 256 , digest_in [255:0] $end
$var wire 512 - message_in [511:0] $end
$var wire 1 ' start_in $end
$var wire 32 . sigma1_wr [31:0] $end
$var wire 32 / sigma0_wr [31:0] $end
$var wire 32 0 h_wr [31:0] $end
$var wire 32 1 g_wr [31:0] $end
$var wire 32 2 f_wr [31:0] $end
$var wire 32 3 e_wr [31:0] $end
$var wire 32 4 e_new_wr [31:0] $end
$var wire 32 5 d_wr [31:0] $end
$var wire 32 6 c_wr [31:0] $end
$var wire 32 7 b_wr [31:0] $end
$var wire 32 8 a_wr [31:0] $end
$var wire 32 9 a_new_wr [31:0] $end
$var wire 32 : W9_wr [31:0] $end
$var wire 32 ; W8_wr [31:0] $end
$var wire 32 < W7_wr [31:0] $end
$var wire 32 = W6_wr [31:0] $end
$var wire 32 > W5_wr [31:0] $end
$var wire 32 ? W4_wr [31:0] $end
$var wire 32 @ W3_wr [31:0] $end
$var wire 32 A W2_wr [31:0] $end
$var wire 32 B W1_wr [31:0] $end
$var wire 32 C W16_wr [31:0] $end
$var wire 32 D W15_wr [31:0] $end
$var wire 32 E W14_wr [31:0] $end
$var wire 32 F W13_wr [31:0] $end
$var wire 32 G W12_wr [31:0] $end
$var wire 32 H W11_wr [31:0] $end
$var wire 32 I W10_wr [31:0] $end
$var wire 32 J W0_wr [31:0] $end
$var reg 32 K K_reg [31:0] $end
$var reg 256 L digest_init_reg [255:0] $end
$var reg 256 M digest_out [255:0] $end
$var reg 256 N digest_reg [255:0] $end
$var reg 512 O message_reg [511:0] $end
$var reg 1 P round_add $end
$var reg 7 Q round_reg [6:0] $end
$var reg 1 ! valid_out $end
$upscope $end
$upscope $end
$enddefinitions $end
#0
$dumpvars
bx Q
xP
b0 O
b0 N
b0 M
b0 L
bx K
b0 J
b0 I
b0 H
b0 G
b0 F
b0 E
b0 D
b0 C
b0 B
b0 A
b0 @
b0 ?
b0 >
b0 =
b0 <
b0 ;
b0 :
bx 9
b0 8
b0 7
b0 6
b0 5
bx 4
b0 3
b0 2
b0 1
b0 0
b0 /
b0 .
b0 -
b0 ,
b0 +
b0 *
b0 )
b0 (
0'
b0 &
b0 %
0$
0#
b0 "
0!
$end
#5000
b1000010100010100010111110011000 9
b1000010100010100010111110011000 4
b1000010100010100010111110011000 K
0P
b0 Q
1#
#10000
0#
#15000
1#
#20000
0#
#25000
1#
#30000
0#
#35000
b1000100110111101111111010111101 *
b1011110011111101110010000101111 9
b11001100111111110010101110010 4
b11010111000101011011010111011010 +
b1000010100010100010111110011000 8
b1000010100010100010111110011000 3
b100001010001010001011111001100000000000000000000000000000000000000000000000000000000000000000000000000000000000000000000000000001000010100010100010111110011000000000000000000000000000000000000000000000000000000000000000000000000000000000000000000000000000 N
1$
1#
#40000
0#
#45000
b1000010000010100010010000001000 )
b1101011101011111011110000101 *
b10101001110101111111010101100101 +
b111100011011000110010110011010 9
b11101100111011000100101000001101 4
b100010100010010100010000 (
b1011110011111101110010000101111 8
b1000010100010100010111110011000 7
b11001100111111110010101110010 3
b1000010100010100010111110011000 2
b101111001111110111001000010111101000010100010100010111110011000000000000000000000000000000000000000000000000000000000000000000000011001100111111110010101110010010000101000101000101111100110000000000000000000000000000000000000000000000000000000000000000000 N
b1100001011000100110001110000000000000000000000000000000000000000000000000000000000000000000000000000000000000000000000000000000000000000000000000000000000000000000000000000000000000000000000000000000000000000000000000000000000000000000000000000000000000000000000000000000000000000000000000000000000000000000000000000000000000000000000000000000000000000000000000000000000000000000000000000000000000000000000000000000000000000000000000000000000000000000000000000000000000000000000000000000000000000000000000011000 &
b1100001011000100110001110000000000000000000000000000000000000000000000000000000000000000000000000000000000000000000000000000000000000000000000000000000000000000000000000000000000000000000000000000000000000000000000000000000000000000000000000000000000000000000000000000000000000000000000000000000000000000000000000000000000000000000000000000000000000000000000000000000000000000000000000000000000000000000000000000000000000000000000000000000000000000000000000000000000000000000000000000000000000000000000000011000 -
b110101000001001111001100110011110111011011001111010111010000101001111000110111011110011011100101010010101001111111101010011101001010001000011100101001001111111100110110000010101101000100011000001111110000011110110011010101101011011111000001100110100011001 %
b110101000001001111001100110011110111011011001111010111010000101001111000110111011110011011100101010010101001111111101010011101001010001000011100101001001111111100110110000010101101000100011000001111110000011110110011010101101011011111000001100110100011001 ,
1#
#50000
0#
#55000
b11001110001000001011010001111110 *
b111010011011111110011001100111 )
b110101100001110010011100101011 +
b11111100001011100100110001100 (
b1100001011000100110001110000000 C
b1100001011000100110001110000000 J
b11000 D
b1101010000010011110011001100111 8
b10111011011001111010111010000101 7
b111100011011101111001101110010 6
b10100101010011111111010100111010 5
b1010001000011100101001001111111 3
b10011011000001010110100010001100 2
b11111100000111101100110101011 1
b1011101011010101110101111001101 9
b11111010001010100100011000100010 4
b1011011111000001100110100011001 0
b11110001101100011001011001101001011110011111101110010000101111010000101000101000101111100110000000000000000000000000000000000011101100111011000100101000001101000110011001111111100101011100100100001010001010001011111001100000000000000000000000000000000000 N
1'
1#
#60000
0#
#65000
b1110001001101110100010010010001 K
b11110000000000000000 .
b10100010100111110110010011010001 *
b1111011011010111110111011000101 )
b1011010100101001111110100101101 +
b1010001000011110110101010101110 (
b11000 E
b11110000000000000000 C
b0 J
b1100001011000100110001110000000 D
b1011101011010101110101111001101 8
b1101010000010011110011001100111 7
b10111011011001111010111010000101 6
b111100011011101111001101110010 5
b11111010001010100100011000100010 3
b1010001000011100101001001111111 2
b10011011000001010110100010001100 1
b1011010011010101101100110101101 9
b1111000110011100111100110001001 4
b11111100000111101100110101011 0
b110101000001001111001100110011110111011011001111010111010000101001111000110111011110011011100101010010101001111111101010011101001010001000011100101001001111111100110110000010101101000100011000001111110000011110110011010101101011011111000001100110100011001 L
b101110101101010111010111100110101101010000010011110011001100111101110110110011110101110100001010011110001101110111100110111001011111010001010100100011000100010010100010000111001010010011111111001101100000101011010001000110000011111100000111101100110101011 N
b1100001100001011000100110001110000000 O
b1 Q
1P
0'
1#
#70000
0#
#75000
b10110101110000001111101111001111 K
b1111101101010000110010000000101 C
b1111101101010000110010000000101 .
b110000100101101101000001010100 *
b1011010011010101110101111101101 )
b1110011111100001110010010010101 +
b1111001000010100100001001110110 (
b11000 F
b1100001011000100110001110000000 E
b11110000000000000000 D
b1011010011010101101100110101101 8
b1011101011010101110101111001101 7
b1101010000010011110011001100111 6
b10111011011001111010111010000101 5
b1111000110011100111100110001001 3
b11111010001010100100011000100010 2
b1010001000011100101001001111111 1
b11001000110000110100011110100111 9
b11111001001010010011100111101011 4
b10011011000001010110100010001100 0
b110000110000101100010011000111000000000000000000011110000000000000000 O
b101101001101010110110011010110101011101011010101110101111001101011010100000100111100110011001111011101101100111101011101000010101111000110011100111100110001001111110100010101001000110001000100101000100001110010100100111111110011011000001010110100010001100 N
b10 Q
1#
#80000
0#
#85000
b11101001101101011101101110100101 K
b1100000000000000000001111000110 C
b1100000000000000000001111000110 .
b11000010000100000000100011010000 *
b1011000011010101100101110101101 )
b110000001110111010000111100 +
b1111010000010100111111110001001 (
b11001000110000110100011110100111 8
b1011010011010101101100110101101 7
b1011101011010101110101111001101 6
b1101010000010011110011001100111 5
b11111001001010010011100111101011 3
b1111000110011100111100110001001 2
b11111010001010100100011000100010 1
b11010101010100001111011001100110 9
b100100111000000000100001010000 4
b1010001000011100101001001111111 0
b11000 G
b1100001011000100110001110000000 F
b11110000000000000000 E
b1111101101010000110010000000101 D
b1100100011000011010001111010011101011010011010101101100110101101010111010110101011101011110011010110101000001001111001100110011111111001001010010011100111101011011110001100111001111001100010011111101000101010010001100010001001010001000011100101001001111111 N
b11000011000010110001001100011100000000000000000001111000000000000000001111101101010000110010000000101 O
b11 Q
1#
#90000
0#
#95000
b111001010101101100001001011011 K
b111110100111010111101101111000 C
b111110100111010111101101111000 .
b1000101101110110000110001001011 *
b11011000010000101101011110100111 )
b111010100100110011010000110010 +
b1111000001011100111100111001001 (
b11000 H
b1100001011000100110001110000000 G
b11110000000000000000 F
b1111101101010000110010000000101 E
b1100000000000000000001111000110 D
b11010101010100001111011001100110 8
b11001000110000110100011110100111 7
b1011010011010101101100110101101 6
b1011101011010101110101111001101 5
b100100111000000000100001010000 3
b11111001001010010011100111101011 2
b1111000110011100111100110001001 1
b100010000001001101001101010 9
b1000011101011011010001001000101 4
b11111010001010100100011000100010 0
b1100001100001011000100110001110000000000000000000111100000000000000000111110110101000011001000000010101100000000000000000001111000110 O
b1101010101010000111101100110011011001000110000110100011110100111010110100110101011011001101011010101110101101010111010111100110100100100111000000000100001010000111110010010100100111001111010110111100011001110011110011000100111111010001010100100011000100010 N
b100 Q
1#
#100000
0#
#105000
b1011001111100010001000111110001 K
b1100000111111110000000000 C
b1100000111111110000000000 .
b1010000001010011010110010001111 *
b11000100010000001101011001100110 )
b10001011011101111110000110011100 +
b10111000101000000001100111101010 (
b100010000001001101001101010 8
b11010101010100001111011001100110 7
b11001000110000110100011110100111 6
b1011010011010101101100110101101 5
b1000011101011011010001001000101 3
b100100111000000000100001010000 2
b11111001001010010011100111101011 1
b101011010000100000100111110101 9
b1110001010000100110000010101101 4
b1111000110011100111100110001001 0
b11000 I
b1100001011000100110001110000000 H
b11110000000000000000 G
b1111101101010000110010000000101 F
b1100000000000000000001111000110 E
b111110100111010111101101111000 D
b10001000000100110100110101011010101010100001111011001100110110010001100001101000111101001110101101001101010110110011010110101000011101011011010001001000101001001001110000000001000010100001111100100101001001110011110101101111000110011100111100110001001 N
b110000110000101100010011000111000000000000000000011110000000000000000011111011010100001100100000001010110000000000000000000111100011000111110100111010111101101111000 O
b101 Q
1#
#110000
0#
#115000
b10010010001111111000001010100100 K
b10010110111001011111111000011 .
b1101010111100000110011000000 *
b101010000001001101001100110 )
b1010110110111011101110110 +
b1000101101000000010100001010101 (
b10010110111001011111111011011 C
b11000 :
b1100001011000100110001110000000 I
b11110000000000000000 H
b1111101101010000110010000000101 G
b1100000000000000000001111000110 F
b111110100111010111101101111000 E
b1100000111111110000000000 D
b101011010000100000100111110101 8
b100010000001001101001101010 7
b11010101010100001111011001100110 6
b11001000110000110100011110100111 5
b1110001010000100110000010101101 3
b1000011101011011010001001000101 2
b100100111000000000100001010000 1
b11100101000000110000001110000000 9
b10011011001001111010010000000001 4
b11111001001010010011100111101011 0
b11000011000010110001001100011100000000000000000001111000000000000000001111101101010000110010000000101011000000000000000000011110001100011111010011101011110110111100000000001100000111111110000000000 O
b10101101000010000010011111010100000100010000001001101001101010110101010101000011110110011001101100100011000011010001111010011101110001010000100110000010101101010000111010110110100010010001010010010011100000000010000101000011111001001010010011100111101011 N
b110 Q
1#
#120000
0#
#125000
b10101011000111000101111011010101 K
b10000001100000000110000000001110 .
b101001010010011110101101101100 *
b100101010000100000101111100000 )
b10101100011011111101010101001 +
b1010001100010100010001001000101 (
b11100101000000110000001110000000 8
b101011010000100000100111110101 7
b100010000001001101001101010 6
b11010101010100001111011001100110 5
b10011011001001111010010000000001 3
b1110001010000100110000010101101 2
b1000011101011011010001001000101 1
b10000101101000000111101101011111 9
b1100011001010111101001111001 4
b100100111000000000100001010000 0
b11000 ;
b11100010111000101100001110001110 C
b1100001011000100110001110000000 :
b11110000000000000000 I
b1111101101010000110010000000101 H
b1100000000000000000001111000110 G
b111110100111010111101101111000 F
b1100000111111110000000000 E
b10010110111001011111111011011 D
b1110010100000011000000111000000000101011010000100000100111110101000001000100000010011010011010101101010101010000111101100110011010011011001001111010010000000001011100010100001001100000101011010100001110101101101000100100010100100100111000000000100001010000 N
b1100001100001011000100110001110000000000000000000111100000000000000000111110110101000011001000000010101100000000000000000001111000110001111101001110101111011011110000000000110000011111111000000000000010010110111001011111111011011 O
b111 Q
1#
#130000
0#
#135000
b11011000000001111010101010011000 K
b11001000000100100101110000011010 .
b10111010011110010100110111000010 *
b10100101000000100000101111010101 )
b10011001101011010010010111000000 +
b1111001001001110010000010000101 (
b11000 <
b1100001011000100110001110000000 ;
b11001000001000010101110000011010 C
b11110000000000000000 :
b1111101101010000110010000000101 I
b1100000000000000000001111000110 H
b111110100111010111101101111000 G
b1100000111111110000000000 F
b10010110111001011111111011011 E
b11100010111000101100001110001110 D
b10000101101000000111101101011111 8
b11100101000000110000001110000000 7
b101011010000100000100111110101 6
b100010000001001101001101010 5
b1100011001010111101001111001 3
b10011011001001111010010000000001 2
b1110001010000100110000010101101 1
b10001110000001001110110010111001 9
b110010110010100010110110001100 4
b1000011101011011010001001000101 0
b110000110000101100010011000111000000000000000000011110000000000000000011111011010100001100100000001010110000000000000000000111100011000111110100111010111101101111000000000011000001111111100000000000001001011011100101111111101101111100010111000101100001110001110 O
b1000010110100000011110110101111111100101000000110000001110000000001010110100001000001001111101010000010001000000100110100110101000001100011001010111101001111001100110110010011110100100000000010111000101000010011000001010110101000011101011011010001001000101 N
b1000 Q
1#
#140000
0#
#145000
b10010100000110101101100000001 K
b111001100011100001010110011101 .
b10101111111111010110100110001 *
b10000101000000000110101110011001 )
b11100100010110111011011111101010 +
b10001001011001011010100000001001 (
b10001110000001001110110010111001 8
b10000101101000000111101101011111 7
b11100101000000110000001110000000 6
b101011010000100000100111110101 5
b110010110010100010110110001100 3
b1100011001010111101001111001 2
b10011011001001111010010000000001 1
b10001100100001110011010001101011 9
b11100110010010010010110010110 4
b1110001010000100110000010101101 0
b11000 =
b1100001011000100110001110000000 <
b11110000000000000000 ;
b10110111001101100111100110100010 C
b1111101101010000110010000000101 :
b1100000000000000000001111000110 I
b111110100111010111101101111000 H
b1100000111111110000000000 G
b10010110111001011111111011011 F
b11100010111000101100001110001110 E
b11001000001000010101110000011010 D
b1000111000000100111011001011100110000101101000000111101101011111111001010000001100000011100000000010101101000010000010011111010100110010110010100010110110001100000011000110010101111010011110011001101100100111101001000000000101110001010000100110000010101101 N
b11000011000010110001001100011100000000000000000001111000000000000000001111101101010000110010000000101011000000000000000000011110001100011111010011101011110110111100000000001100000111111110000000000000100101101110010111111110110111110001011100010110000111000111011001000001000010101110000011010 O
b1001 Q
1#
#150000
0#
#155000
b100100001100011000010110111110 K
b10000101101111000011010101000011 .
b1011100101011000000011100010001 *
b10001100100001000111110001111011 )
b10001110001000100111011010111100 +
b10000111011000111111111101101 (
b11000 >
b1100001011000100110001110000000 =
b11110000000000000000 <
b1111101101010000110010000000101 ;
b11100101101111000011100100001001 C
b1100000000000000000001111000110 :
b111110100111010111101101111000 I
b1100000111111110000000000 H
b10010110111001011111111011011 G
b11100010111000101100001110001110 F
b11001000001000010101110000011010 E
b10110111001101100111100110100010 D
b10001100100001110011010001101011 8
b10001110000001001110110010111001 7
b10000101101000000111101101011111 6
b11100101000000110000001110000000 5
b11100110010010010010110010110 3
b110010110010100010110110001100 2
b1100011001010111101001111001 1
b1000111100110001010001111110100 9
b1000011011010110010001111101000 4
b10011011001001111010010000000001 0
b1100001100001011000100110001110000000000000000000111100000000000000000111110110101000011001000000010101100000000000000000001111000110001111101001110101111011011110000000000110000011111111000000000000010010110111001011111111011011111000101110001011000011100011101100100000100001010111000001101010110111001101100111100110100010 O
b1000110010000111001101000110101110001110000001001110110010111001100001011010000001111011010111111110010100000011000000111000000000011100110010010010010110010110001100101100101000101101100011000000110001100101011110100111100110011011001001111010010000000001 N
b1010 Q
1#
#160000
0#
